[
    {
        "sourceSystem":"SYS0021",
        "targetTableName":"PTY_TEL",
        "order":"1",
        "sourcePrimaryTable":{
            "tableName":"SYS0021.C_IDS_PHONE_TBL",
            "alias":"PHONE"
        },
        "combinationMap":[
            {
                "alias":"id",
                "specialHandle":{
                    "handleName":"decode",
                    "parameters":[
                        "${PERSON.id}",
                        "",
                        "${PERSON.id15}",
                        "${PERSON.id}"
                    ]
                }
            },
            {
                "alias":"cust_id",
                "specialHandle":{
                    "handleName":"CustFlgHandler",
                    "parameters":[
                        "${id}",
                        "${PERSON.idtype}",
                        "${PERSON.name}"
                    ]
                }
            },
            {
                "alias":"md5TelCust_id",
                "specialHandle":{
                    "handleName":"md5",
                    "parameters":[
                        "${cust_id}"
                    ]
                }
            }
        ],
        "rowKey":[
            "${md5TelCust_id}",
            "${cust_id}",
             "SYS0021",
            "${PHONE.usage}"
        ],
        "relations":[
            {
                "sourceTableName":"SYS0021.MAX_PERSON",
                "alias":"PERSON",
                "relationType":"inner",
                "on":{
                    "operatorSymbol":"and",
                    "conditionList":[
                        {
                            "conditionType":"simple",
                            "conditionContext":{
                                "expression":{
                                    "expressionType":"=",
                                    "dataType":"String",
                                    "formatter":""
                                },
                                "leftCondition":"${PERSON.source_person_id}",
                                "rightCondition":"${PHONE.source_person_id}"
                            }
                        }
                    ]
                }
            }
        ],
        "where":{
            "operatorSymbol":"and",
            "conditionList":[
                {
                    "conditionType":"simple",
                    "conditionContext":{
                        "expression":{
                            "expressionType":"<>",
                            "dataType":"String",
                            "formatter":""
                        },
                        "leftCondition":"${PHONE.tel}",
                        "rightCondition":""
                    }
                },
                {
                    "conditionType":"simple",
                    "conditionContext":{
                        "expression":{
                            "expressionType":"<>",
                            "dataType":"String",
                            "formatter":""
                        },
                        "leftCondition":"${PHONE.usage}",
                        "rightCondition":""
                    }
                }
            ]
        },
        "columnList":[
            {
                "srcColumnName":"${cust_id}",
                "dstColumnName":"cust_id",
                "validate":"",
                "priority":""
            },
            {
                "srcColumnName":"1",
                "dstColumnName":"custtype",
                "validate":"",
                "priority":""
            },
            {
                "srcColumnName":"${PHONE.usage}",
                "dstColumnName":"teltype",
                "validate":"",
                "priority":""
            },
            {
                "srcColumnName":"${PHONE.countrycode}",
                "dstColumnName":"country",
                "validate":"",
                "priority":""
            },
            {
                "srcColumnName":"${PHONE.areacode}",
                "dstColumnName":"areacode",
                "validate":"",
                "priority":""
            },
            {
                "srcColumnName":"${PHONE.tel}",
                "dstColumnName":"tel",
                "validate":"",
                "priority":""
            },
            {
                "srcColumnName":"${PHONE.ext}",
                "dstColumnName":"tel_ext",
                "validate":"",
                "priority":""
            },
            {
                "srcColumnName":"${PHONE.telnumber}",
                "dstColumnName":"full_tel",
                "validate":"",
                "priority":""
            },
            {
                "srcColumnName":"${PHONE.contacted_ind}",
                "dstColumnName":"succ_contactflg",
                "validate":"",
                "priority":""
            },
            {
                "srcColumnName":"${PHONE.purpose}",
                "dstColumnName":"main_telflg",
                "validate":"",
                "priority":""
            },
            {
                "srcColumnName":"${PHONE.del_date}",
                "dstColumnName":"crt_tm",
                "validate":"",
                "priority":""
            },
	        {
	        	"srcColumnName":{
	                "handleName":"telFlg",
	                "parameters":
	                [	                    
	                    "${PHONE.tel}"
	                   
	                ]
	            },
	            "dstColumnName":"is_valid",
	            "validate":"",
	            "priority":""
	        }
        ]
    },
    {
        "sourceSystem":"SYS0021",
        "targetTableName":"PTY_TEL",
        "order":"2",
        "sourcePrimaryTable":{
            "tableName":"SYS0021.C_IDS_PHONE_TBL",
            "alias":"PHONE"
        },
        "combinationMap":[
            {
                "alias":"id",
                "specialHandle":{
                    "handleName":"decode",
                    "parameters":[
                        "${PERSON.id}",
                        "",
                        "${PERSON.id15}",
                        "${PERSON.id}"
                    ]
                }
            },
            {
                "alias": "concatSRC_CUST_ID",
                "specialHandle": {
                    "handleName": "contact",
                    "parameters": [
                        "EX_SYS0021_C_IDS_PERSON_TBL*||*00*||*SOURCE_PERSON_ID*||*",
                        "${PERSON.source_person_id}"
                    ]
                }
            },
            {
                "alias":"tel_cust_id",
                "specialHandle":{
                    "handleName":"CustFlgTmpHandler",
                    "parameters":[
                        "${id}",
                        "${PERSON.idtype}",
                        "${PERSON.name}",
                        "${concatSRC_CUST_ID}"
                    ]
                }
            },
            {
                "alias":"md5TelCust_id",
                "specialHandle":{
                    "handleName":"md5",
                    "parameters":[
                        "${tel_cust_id}"
                    ]
                }
            }
        ],
        "rowKey":[
            "${md5TelCust_id}",
            "${tel_cust_id}",
            "SYS0021",
            "${PHONE.usage}"
        ],
        "relations":[
            {
                "sourceTableName":"SYS0021.MAX_PERSON",
                "alias":"PERSON",
                "relationType":"inner",
                "on":{
                    "operatorSymbol":"and",
                    "conditionList":[
                        {
                            "conditionType":"simple",
                            "conditionContext":{
                                "expression":{
                                    "expressionType":"=",
                                    "dataType":"String",
                                    "formatter":""
                                },
                                "leftCondition":"${PERSON.source_person_id}",
                                "rightCondition":"${PHONE.source_person_id}"
                            }
                        }
                    ]
                }
            }
        ],
        "where":{
            "operatorSymbol":"and",
            "conditionList":[
                {
                    "conditionType":"simple",
                    "conditionContext":{
                        "expression":{
                            "expressionType":"<>",
                            "dataType":"String",
                            "formatter":""
                        },
                        "leftCondition":"${PHONE.tel}",
                        "rightCondition":""
                    }
                },
                {
                    "conditionType":"simple",
                    "conditionContext":{
                        "expression":{
                            "expressionType":"<>",
                            "dataType":"String",
                            "formatter":""
                        },
                        "leftCondition":"${PHONE.usage}",
                        "rightCondition":""
                    }
                },
                {
                    "conditionType":"simple",
                    "conditionContext":{
                        "expression":{
                            "expressionType":"<>",
                            "dataType":"String",
                            "formatter":""
                        },
                        "leftCondition":"${tel_cust_id}",
                        "rightCondition":""
                    }
                }
            ]
        },
        "columnList":[
            {
                "srcColumnName":"${tel_cust_id}",
                "dstColumnName":"cust_id",
                "validate":"",
                "priority":""
            },
            {
                "srcColumnName":"3",
                "dstColumnName":"custtype",
                "validate":"",
                "priority":""
            },
            {
                "srcColumnName":"${PHONE.usage}",
                "dstColumnName":"teltype",
                "validate":"",
                "priority":""
            },
            {
                "srcColumnName":"${PHONE.countrycode}",
                "dstColumnName":"country",
                "validate":"",
                "priority":""
            },
            {
                "srcColumnName":"${PHONE.areacode}",
                "dstColumnName":"areacode",
                "validate":"",
                "priority":""
            },
            {
                "srcColumnName":"${PHONE.tel}",
                "dstColumnName":"tel",
                "validate":"",
                "priority":""
            },
            {
                "srcColumnName":"${PHONE.ext}",
                "dstColumnName":"tel_ext",
                "validate":"",
                "priority":""
            },
            {
                "srcColumnName":"${PHONE.telnumber}",
                "dstColumnName":"full_tel",
                "validate":"",
                "priority":""
            },
            {
                "srcColumnName":"${PHONE.contacted_ind}",
                "dstColumnName":"succ_contactflg",
                "validate":"",
                "priority":""
            },
            {
                "srcColumnName":"${PHONE.purpose}",
                "dstColumnName":"main_telflg",
                "validate":"",
                "priority":""
            },
            {
                "srcColumnName":"${PHONE.del_date}",
                "dstColumnName":"crt_tm",
                "validate":"",
                "priority":""
            },
	        {
	        	"srcColumnName":{
	                "handleName":"telFlg",
	                "parameters":
	                [	                    
	                    "${PHONE.tel}"
	                   
	                ]
	            },
	            "dstColumnName":"is_valid",
	            "validate":"",
	            "priority":""
	        }
        ]
    }
]